pygtranslate/__init__.py
pygtranslate/translator.py
pygtranslate-0.0.1.dist-info/METADATA
pygtranslate-0.0.1.dist-info/RECORD
pygtranslate-0.0.1.dist-info/WHEEL
pygtranslate-0.0.1.dist-info/top_level.txt
