Metadata-Version: 2.1
Name: pygtranslate
Version: 0.0.1
Summary: Pythonic interface to google translate services
Home-page: https://github.com/varunbalupuri/gtranslate-python
Author: Varun Balupuri
Author-email: varunbalupuri@gmail.com
License: UNKNOWN
Download-URL: https://github.com/varunbalupuri/gtranslate-python/archive/0.1.tar.gz
Keywords: translation,google translate,translate
Platform: UNKNOWN
Requires-Dist: requests
